README.md
setup.cfg
setup.py
virustotal3/__init__.py
virustotal3/core.py
virustotal3/enterprise.py
virustotal3/errors.py
virustotal3.egg-info/PKG-INFO
virustotal3.egg-info/SOURCES.txt
virustotal3.egg-info/dependency_links.txt
virustotal3.egg-info/requires.txt
virustotal3.egg-info/top_level.txt