Metadata-Version: 2.1
Name: virustotal3
Version: 1.0.6
Summary: Python 3 implementation of the VirusTotal v3 API
Home-page: https://github.com/tr4cefl0w/virustotal3.git
Author: tr4cefl0w
Author-email: tr4cefl0w@protonmail.com
License: UNKNOWN
Platform: UNKNOWN
Classifier: Programming Language :: Python :: 3
Classifier: Operating System :: OS Independent
